ine_tugesto_somenergia
