Metadata-Version: 1.1
Name: ine-tugesto-somenergia
Version: 1.0.0.1
Summary: Translates INE to Tugesto ids
Home-page: https://github.com/som-energia/ine_tugesto
Author: Som Energia
Author-email: info@somenergia.coop
License: MIT
Platform: UNKNOWN
Classifier: Programming Language :: Python :: 2.7
Classifier: Operating System :: OS Independent
